{

"images": [
    "multiple_choice_choice_button_get_right_sprite.png.png"
],

"frames": [
    [1, 1, 405, 67, 0, -2, -1],
    [1, 70, 405, 67, 0, -2, -1],
    [1, 139, 405, 67, 0, -2, -1]
],

"animations": {
    "0": [0],
    "1": [1],
    "3": [2]
},

"texturepacker": [
        "SmartUpdateHash: $TexturePacker:SmartUpdate:5ede708f976b063ad8c2095c6f5384c1:3b66b7c37a13088734c5e83a4d82101a:c8e622b1cac1ec59d49eda79437fc3f8$",
        "Created with TexturePacker (https://www.codeandweb.com/texturepacker) for EaselJS"
]

}
