{

    "images": [
    "yellow_line_big_bubble.png"
],

    "frames": [
    [1, 1, 51, 73, 0, 0, 0],
    [1, 76, 51, 73, 0, 0, 0],
    [1, 151, 51, 73, 0, 0, 0],
    [1, 226, 51, 73, 0, 0, 0]
],

    "animations": {
        "white": [0],
        "grey": [1],
        "red": [2],
        "green": [3]
    },

    "texturepacker": [
        "SmartUpdateHash: $TexturePacker:SmartUpdate:c1978ee7ef8f5d7a0b4fcb87d9684b15:f37700c4a916cba3f01b8001e687f619:d3ce95449aa0226cbc657677f42d570a$",
        "Created with TexturePacker (https://www.codeandweb.com/texturepacker) for EaselJS"
]

}